{
    "processing_elements": [
        8,
        24
    ],
    "frequency_mhz": 250,
    "bits_input": 4,
    "bits_weights": 4,
    "bits_sum": 32,
    "bits_bias": 16,
    "max_batch_size": 64,
    "max_channels_in": 2048,
    "max_kernel_size": 9,
    "max_image_size": 512,
    "max_n_bundles": 64,
    "ram_weights_depth": 20,
    "ram_edges_depth": 288,
    "axi_width": 128,
    "header_width": 64,
    "config_baseaddr": "B0000000",
    "axi_max_burst_len": 16,
    "target_cpu_int_bits": 32,
    "async_resetn": true,
    "valid_prob": 0.1,
    "ready_prob": 0.01,
    "data_dir": "vectors"
}